accounts/__init__.py
accounts/admin.py
accounts/apps.py
accounts/models.py
accounts/permissions.py
accounts/serializers.py
accounts/urls.py
accounts/views.py
accounts/migrations/0001_initial.py
accounts/migrations/__init__.py
django_basic_jwt_auth-0.2.dist-info/LICENSE
django_basic_jwt_auth-0.2.dist-info/METADATA
django_basic_jwt_auth-0.2.dist-info/WHEEL
django_basic_jwt_auth-0.2.dist-info/top_level.txt
django_basic_jwt_auth-0.2.dist-info/RECORD
