Metadata-Version: 2.1
Name: django-basic-jwt-auth
Version: 0.2
Summary: Accounts is a Django app to authenticate user using JWT Toke on custom users.
Home-page: https://github.com/niomwungeri-fabrice/django-basic-jwt-auth
Author: Fabrice NIYOMWUNGERI
Author-email: niomwungeri.fabrice@gmail.com
License: UNKNOWN
Platform: UNKNOWN
Classifier: Environment :: Web Environment
Classifier: Framework :: Django
Classifier: Framework :: Django :: 2.2
Classifier: Intended Audience :: Developers
Classifier: License :: OSI Approved :: GNU General Public License v3 (GPLv3)
Classifier: Operating System :: OS Independent
Classifier: Programming Language :: Python
Classifier: Programming Language :: Python :: 3
Classifier: Programming Language :: Python :: 3 :: Only
Classifier: Programming Language :: Python :: 3.6
Classifier: Programming Language :: Python :: 3.7
Classifier: Topic :: Internet :: WWW/HTTP
Classifier: Topic :: Internet :: WWW/HTTP :: Dynamic Content
